noselongdescription
