Metadata-Version: 1.0
Name: nose-long-description
Version: 0.2
Summary: A nose plugin that combines the name and docstring of a test when describing it.
Home-page: UNKNOWN
Author: Matthew J Desmarais
Author-email: matthew.desmarais@gmail.com
License: MIT
Platform: UNKNOWN
